[
  {
    "ContainingType": "CinemaBackend.Controllers.AuditoriumApiController",
    "Method": "GetAuditoriums",
    "RelativePath": "api/AuditoriumApi",
    "HttpMethod": "GET",
    "IsController": true,
    "Order": 0,
    "Parameters": [],
    "ReturnTypes": [
      {
        "Type": "System.Collections.Generic.IEnumerable\u00601[[CinemaBackend.DTO.AuditoriumDTO, CinemaBackend, Version=1.0.0.0, Culture=neutral, PublicKeyToken=null]]",
        "MediaTypes": [
          "text/plain",
          "application/json",
          "text/json"
        ],
        "StatusCode": 200
      }
    ]
  },
  {
    "ContainingType": "CinemaBackend.Controllers.AuditoriumApiController",
    "Method": "CreateAuditorium",
    "RelativePath": "api/AuditoriumApi",
    "HttpMethod": "POST",
    "IsController": true,
    "Order": 0,
    "Parameters": [
      {
        "Name": "auditoriumDTO",
        "Type": "CinemaBackend.DTO.AuditoriumDTO",
        "IsRequired": true
      }
    ],
    "ReturnTypes": [
      {
        "Type": "CinemaBackend.DTO.AuditoriumDTO",
        "MediaTypes": [
          "text/plain",
          "application/json",
          "text/json"
        ],
        "StatusCode": 200
      }
    ]
  },
  {
    "ContainingType": "CinemaBackend.Controllers.AuditoriumApiController",
    "Method": "GetAuditorium",
    "RelativePath": "api/AuditoriumApi/{id}",
    "HttpMethod": "GET",
    "IsController": true,
    "Order": 0,
    "Parameters": [
      {
        "Name": "id",
        "Type": "System.Int32",
        "IsRequired": true
      }
    ],
    "ReturnTypes": [
      {
        "Type": "CinemaBackend.DTO.AuditoriumDTO",
        "MediaTypes": [
          "text/plain",
          "application/json",
          "text/json"
        ],
        "StatusCode": 200
      }
    ]
  },
  {
    "ContainingType": "CinemaBackend.Controllers.AuditoriumApiController",
    "Method": "UpdateAuditorium",
    "RelativePath": "api/AuditoriumApi/{id}",
    "HttpMethod": "PUT",
    "IsController": true,
    "Order": 0,
    "Parameters": [
      {
        "Name": "id",
        "Type": "System.Int32",
        "IsRequired": true
      },
      {
        "Name": "auditoriumDTO",
        "Type": "CinemaBackend.DTO.AuditoriumDTO",
        "IsRequired": true
      }
    ],
    "ReturnTypes": []
  },
  {
    "ContainingType": "CinemaBackend.Controllers.AuditoriumApiController",
    "Method": "DeleteAuditorium",
    "RelativePath": "api/AuditoriumApi/{id}",
    "HttpMethod": "DELETE",
    "IsController": true,
    "Order": 0,
    "Parameters": [
      {
        "Name": "id",
        "Type": "System.Int32",
        "IsRequired": true
      }
    ],
    "ReturnTypes": []
  },
  {
    "ContainingType": "CinemaBackend.Controllers.CinemaApiController",
    "Method": "GetCinemas",
    "RelativePath": "api/CinemaApi",
    "HttpMethod": "GET",
    "IsController": true,
    "Order": 0,
    "Parameters": [],
    "ReturnTypes": [
      {
        "Type": "System.Collections.Generic.IEnumerable\u00601[[CinemaBackend.DTO.CinemaDTO, CinemaBackend, Version=1.0.0.0, Culture=neutral, PublicKeyToken=null]]",
        "MediaTypes": [
          "text/plain",
          "application/json",
          "text/json"
        ],
        "StatusCode": 200
      }
    ]
  },
  {
    "ContainingType": "CinemaBackend.Controllers.CinemaApiController",
    "Method": "CreateCinema",
    "RelativePath": "api/CinemaApi",
    "HttpMethod": "POST",
    "IsController": true,
    "Order": 0,
    "Parameters": [
      {
        "Name": "cinemaDTO",
        "Type": "CinemaBackend.DTO.CinemaDTO",
        "IsRequired": true
      }
    ],
    "ReturnTypes": [
      {
        "Type": "CinemaBackend.DTO.CinemaDTO",
        "MediaTypes": [
          "text/plain",
          "application/json",
          "text/json"
        ],
        "StatusCode": 200
      }
    ]
  },
  {
    "ContainingType": "CinemaBackend.Controllers.CinemaApiController",
    "Method": "GetCinema",
    "RelativePath": "api/CinemaApi/{id}",
    "HttpMethod": "GET",
    "IsController": true,
    "Order": 0,
    "Parameters": [
      {
        "Name": "id",
        "Type": "System.Int32",
        "IsRequired": true
      }
    ],
    "ReturnTypes": [
      {
        "Type": "CinemaBackend.DTO.CinemaDTO",
        "MediaTypes": [
          "text/plain",
          "application/json",
          "text/json"
        ],
        "StatusCode": 200
      }
    ]
  },
  {
    "ContainingType": "CinemaBackend.Controllers.CinemaApiController",
    "Method": "UpdateCinema",
    "RelativePath": "api/CinemaApi/{id}",
    "HttpMethod": "PUT",
    "IsController": true,
    "Order": 0,
    "Parameters": [
      {
        "Name": "id",
        "Type": "System.Int32",
        "IsRequired": true
      },
      {
        "Name": "cinemaDTO",
        "Type": "CinemaBackend.DTO.CinemaDTO",
        "IsRequired": true
      }
    ],
    "ReturnTypes": []
  },
  {
    "ContainingType": "CinemaBackend.Controllers.CinemaApiController",
    "Method": "DeleteCinema",
    "RelativePath": "api/CinemaApi/{id}",
    "HttpMethod": "DELETE",
    "IsController": true,
    "Order": 0,
    "Parameters": [
      {
        "Name": "id",
        "Type": "System.Int32",
        "IsRequired": true
      }
    ],
    "ReturnTypes": []
  },
  {
    "ContainingType": "CinemaBackend.Controllers.MoviesApiController",
    "Method": "GetMovies",
    "RelativePath": "api/MoviesApi",
    "HttpMethod": "GET",
    "IsController": true,
    "Order": 0,
    "Parameters": [],
    "ReturnTypes": [
      {
        "Type": "System.Collections.Generic.IEnumerable\u00601[[CinemaBackend.DTO.MovieDTO, CinemaBackend, Version=1.0.0.0, Culture=neutral, PublicKeyToken=null]]",
        "MediaTypes": [
          "text/plain",
          "application/json",
          "text/json"
        ],
        "StatusCode": 200
      }
    ]
  },
  {
    "ContainingType": "CinemaBackend.Controllers.MoviesApiController",
    "Method": "PostMovie",
    "RelativePath": "api/MoviesApi",
    "HttpMethod": "POST",
    "IsController": true,
    "Order": 0,
    "Parameters": [
      {
        "Name": "movieDto",
        "Type": "CinemaBackend.DTO.MovieDTO",
        "IsRequired": true
      }
    ],
    "ReturnTypes": [
      {
        "Type": "CinemaBackend.DTO.MovieDTO",
        "MediaTypes": [
          "text/plain",
          "application/json",
          "text/json"
        ],
        "StatusCode": 200
      }
    ]
  },
  {
    "ContainingType": "CinemaBackend.Controllers.MoviesApiController",
    "Method": "GetMovie",
    "RelativePath": "api/MoviesApi/{id}",
    "HttpMethod": "GET",
    "IsController": true,
    "Order": 0,
    "Parameters": [
      {
        "Name": "id",
        "Type": "System.Int32",
        "IsRequired": true
      }
    ],
    "ReturnTypes": [
      {
        "Type": "CinemaBackend.DTO.MovieDTO",
        "MediaTypes": [
          "text/plain",
          "application/json",
          "text/json"
        ],
        "StatusCode": 200
      }
    ]
  },
  {
    "ContainingType": "CinemaBackend.Controllers.MoviesApiController",
    "Method": "PutMovie",
    "RelativePath": "api/MoviesApi/{id}",
    "HttpMethod": "PUT",
    "IsController": true,
    "Order": 0,
    "Parameters": [
      {
        "Name": "id",
        "Type": "System.Int32",
        "IsRequired": true
      },
      {
        "Name": "movieDto",
        "Type": "CinemaBackend.DTO.MovieDTO",
        "IsRequired": true
      }
    ],
    "ReturnTypes": []
  },
  {
    "ContainingType": "CinemaBackend.Controllers.MoviesApiController",
    "Method": "DeleteMovie",
    "RelativePath": "api/MoviesApi/{id}",
    "HttpMethod": "DELETE",
    "IsController": true,
    "Order": 0,
    "Parameters": [
      {
        "Name": "id",
        "Type": "System.Int32",
        "IsRequired": true
      }
    ],
    "ReturnTypes": []
  },
  {
    "ContainingType": "CinemaBackend.Controllers.ReservationsApiController",
    "Method": "GetReservations",
    "RelativePath": "api/ReservationsApi",
    "HttpMethod": "GET",
    "IsController": true,
    "Order": 0,
    "Parameters": [],
    "ReturnTypes": []
  },
  {
    "ContainingType": "CinemaBackend.Controllers.ReservationsApiController",
    "Method": "CreateReservation",
    "RelativePath": "api/ReservationsApi",
    "HttpMethod": "POST",
    "IsController": true,
    "Order": 0,
    "Parameters": [
      {
        "Name": "reservationDTO",
        "Type": "CinemaBackend.DTO.ReservationDTO",
        "IsRequired": true
      }
    ],
    "ReturnTypes": []
  },
  {
    "ContainingType": "CinemaBackend.Controllers.ReservationsApiController",
    "Method": "GetReservation",
    "RelativePath": "api/ReservationsApi/{id}",
    "HttpMethod": "GET",
    "IsController": true,
    "Order": 0,
    "Parameters": [
      {
        "Name": "id",
        "Type": "System.Int32",
        "IsRequired": true
      }
    ],
    "ReturnTypes": []
  },
  {
    "ContainingType": "CinemaBackend.Controllers.ReservationsApiController",
    "Method": "UpdateReservation",
    "RelativePath": "api/ReservationsApi/{id}",
    "HttpMethod": "PUT",
    "IsController": true,
    "Order": 0,
    "Parameters": [
      {
        "Name": "id",
        "Type": "System.Int32",
        "IsRequired": true
      },
      {
        "Name": "reservationDTO",
        "Type": "CinemaBackend.DTO.ReservationDTO",
        "IsRequired": true
      }
    ],
    "ReturnTypes": []
  },
  {
    "ContainingType": "CinemaBackend.Controllers.ReservationsApiController",
    "Method": "DeleteReservation",
    "RelativePath": "api/ReservationsApi/{id}",
    "HttpMethod": "DELETE",
    "IsController": true,
    "Order": 0,
    "Parameters": [
      {
        "Name": "id",
        "Type": "System.Int32",
        "IsRequired": true
      }
    ],
    "ReturnTypes": []
  },
  {
    "ContainingType": "CinemaBackend.Controllers.TransactionsApiController",
    "Method": "GetTransactions",
    "RelativePath": "api/TransactionsApi",
    "HttpMethod": "GET",
    "IsController": true,
    "Order": 0,
    "Parameters": [],
    "ReturnTypes": []
  },
  {
    "ContainingType": "CinemaBackend.Controllers.TransactionsApiController",
    "Method": "CreateTransaction",
    "RelativePath": "api/TransactionsApi",
    "HttpMethod": "POST",
    "IsController": true,
    "Order": 0,
    "Parameters": [
      {
        "Name": "transactionDTO",
        "Type": "CinemaBackend.DTO.TransactionDTO",
        "IsRequired": true
      }
    ],
    "ReturnTypes": []
  },
  {
    "ContainingType": "CinemaBackend.Controllers.TransactionsApiController",
    "Method": "GetTransaction",
    "RelativePath": "api/TransactionsApi/{id}",
    "HttpMethod": "GET",
    "IsController": true,
    "Order": 0,
    "Parameters": [
      {
        "Name": "id",
        "Type": "System.Int32",
        "IsRequired": true
      }
    ],
    "ReturnTypes": []
  },
  {
    "ContainingType": "CinemaBackend.Controllers.TransactionsApiController",
    "Method": "UpdateTransaction",
    "RelativePath": "api/TransactionsApi/{id}",
    "HttpMethod": "PUT",
    "IsController": true,
    "Order": 0,
    "Parameters": [
      {
        "Name": "id",
        "Type": "System.Int32",
        "IsRequired": true
      },
      {
        "Name": "transactionDTO",
        "Type": "CinemaBackend.DTO.TransactionDTO",
        "IsRequired": true
      }
    ],
    "ReturnTypes": []
  },
  {
    "ContainingType": "CinemaBackend.Controllers.TransactionsApiController",
    "Method": "DeleteTransaction",
    "RelativePath": "api/TransactionsApi/{id}",
    "HttpMethod": "DELETE",
    "IsController": true,
    "Order": 0,
    "Parameters": [
      {
        "Name": "id",
        "Type": "System.Int32",
        "IsRequired": true
      }
    ],
    "ReturnTypes": []
  }
]